Metadata-Version: 2.1
Name: libeeg
Version: 1.0.0
Summary: Library with various functions.
Author-email: sas.grebencin@gmail.com
